tikz2graphml/CustomTikzListener.py
tikz2graphml/Gui.py
tikz2graphml/TikzErrorListener.py
tikz2graphml/__init__.py
tikz2graphml/__main__.py
tikz2graphml/extradeCodeInsideTikzAndUnrollForeach.py
tikz2graphml/filterGraphml.py
tikz2graphml/generateGraphml.py
tikz2graphml/parseTikz.py
tikz2graphml/parsingUtils.py
tikz2graphml/grammar/TikzLexer.py
tikz2graphml/grammar/TikzListener.py
tikz2graphml/grammar/TikzParser.py
tikz2graphml/grammar/__init__.py
tikz2graphml/pyyed/__init__.py
tikz2graphml-1.1.2.dist-info/LICENSE
tikz2graphml-1.1.2.dist-info/METADATA
tikz2graphml-1.1.2.dist-info/NOTICE
tikz2graphml-1.1.2.dist-info/WHEEL
tikz2graphml-1.1.2.dist-info/entry_points.txt
tikz2graphml-1.1.2.dist-info/top_level.txt
tikz2graphml-1.1.2.dist-info/RECORD
