Metadata-Version: 2.1
Name: tikz2graphml
Version: 1.1.2
Summary: Convert Latex Tikz code into yed graphml
Home-page: https://github.com/ysahil97/tikz-to-yed-graphml
Author: Harsh Agarwal
Author-email: harshaga97@gmail.com
License: UNKNOWN
Platform: UNKNOWN
Requires-Dist: colour (==0.1.5)
Requires-Dist: numpy (==1.16.2)
Requires-Dist: networkx (==2.3)
Requires-Dist: matplotlib (==3.0.3)
Requires-Dist: pylatexenc (==1.4)
Requires-Dist: antlr4-python3-runtime (==4.7.2)
